{
 "actions": [],
 "allow_rename": 1,
 "creation": "2024-11-04 22:54:51.577579",
 "doctype": "DocType",
 "editable_grid": 1,
 "engine": "InnoDB",
 "field_order": [
  "employee"
 ],
 "fields": [
  {
   "fieldname": "employee",
   "fieldtype": "Link",
   "in_filter": 1,
   "in_list_view": 1,
   "in_preview": 1,
   "in_standard_filter": 1,
   "label": "Employee",
   "options": "Employee"
  }
 ],
 "index_web_pages_for_search": 1,
 "istable": 1,
 "links": [],
 "modified": "2024-11-04 22:55:45.281690",
 "modified_by": "Administrator",
 "module": "HR VentureForce Global",
 "name": "Late Relaxation Employee List",
 "owner": "Administrator",
 "permissions": [],
 "sort_field": "modified",
 "sort_order": "DESC",
 "states": []
}